libpttea/__init__.py
libpttea/api.py
libpttea/data_processor.py
libpttea/exceptions.py
libpttea/navigator.py
libpttea/pattern.py
libpttea/ptt_action.py
libpttea/ptt_functions.py
libpttea/router.py
libpttea/sessions.py
libpttea/websocket_client.py
libpttea-1.1.0.dist-info/LICENSE
libpttea-1.1.0.dist-info/METADATA
libpttea-1.1.0.dist-info/WHEEL
libpttea-1.1.0.dist-info/RECORD
