Metadata-Version: 2.1
Name: libpttea
Version: 1.1.0
Summary: A Python library that encapsulates various PTT functions.
Home-page: https://github.com/bubble-tea-project/libpttea
License: LGPL-3.0-or-later
Author: vHrqO
Author-email: you@example.com
Requires-Python: >=3.10,<4.0
Classifier: License :: OSI Approved :: GNU Lesser General Public License v3 or later (LGPLv3+)
Classifier: Programming Language :: Python :: 3
Classifier: Programming Language :: Python :: 3.10
Classifier: Programming Language :: Python :: 3.11
Classifier: Programming Language :: Python :: 3.12
Classifier: Programming Language :: Python :: 3.13
Requires-Dist: ansiparser (>=1.2.0,<2.0.0)
Requires-Dist: websockets (>=13.1,<14.0)
Project-URL: Repository, https://github.com/bubble-tea-project/libpttea
